[{"title":"css复习记录","url":"/2018/11/14/css复习记录/"},{"title":"hexo next配置及插件(自己经历的坑)","url":"/2018/11/13/hexo配置及插件-自己经历的坑/"},{"title":"html复习记录","url":"/2018/11/14/html复习记录/"},{"title":"js复习记录","url":"/2018/11/14/js复习记录/"},{"title":"php学习记录","url":"/2018/12/02/php学习记录/"},{"title":"poj2083","url":"/2018/11/14/poj2083/"},{"title":"python学习","url":"/2018/11/14/python学习/"},{"title":"字符串处理","url":"/2018/11/19/字符串处理/"},{"title":"分治算法","url":"/2018/11/15/分治算法/"},{"title":"我的博客","url":"/2018/11/11/我的博客/"},{"title":"正则表达式学习","url":"/2018/11/14/正则表达式学习/"},{"title":"排序","url":"/2018/11/19/排序/"},{"title":"排序Ex","url":"/2018/11/19/排序Ex/"},{"title":"洛谷_普及组_交叉模拟","url":"/2018/11/14/洛谷-普及组-交叉模拟/"},{"title":"洛谷_普及组_简单的模拟","url":"/2018/11/12/洛谷-普及组-简单的模拟/"},{"title":"简单字符串","url":"/2018/11/16/简单字符串/"},{"title":"记录心情的日志","url":"/2018/11/18/记录心情的日志/"},{"title":"贪心","url":"/2018/11/21/贪心/"},{"title":"高精度算法","url":"/2018/11/26/高精度算法/"}]